{
  "id": "f9138fbf-f695-4172-9e30-388605020c81",
  "name": "Rally",
  "type": "ABILITY",
  "quality": "RARE",
  "image": "https://media.discordapp.net/attachments/954643538342182924/1008686932940816475/unknown.jpeg",
  "imageSize": "150%",
  "body": "Pay 5 charge.\nUntil your next turn, any ally which starts or ends their turn within your reach restores 2 health.",
  "flavor": null,
  "author": null,
  "editionId": null,
  "fontSize": "10pt",
  "bodyOpacity": 80.0,
  "costInExperience": 0,
  "prerequisites": {
    "attributePrerequisites": [],
    "skillPrerequisites": [],
    "cardPrerequisites": []
  },
  "fullArt": false,
  "darkText": true
}